pyros_interfaces.common-0.4.1-py2.7-nspkg.pth
pyros_interfaces/common/__init__.py
pyros_interfaces/common/_version.py
pyros_interfaces/common/basemsg.py
pyros_interfaces/common/basenode.py
pyros_interfaces/common/exceptions.py
pyros_interfaces/common/pyros_prtcl.py
pyros_interfaces/common/regex_tools.py
pyros_interfaces/common/transient.py
pyros_interfaces/common/transient_if.py
pyros_interfaces/common/transient_if_pool.py
pyros_interfaces/common/utils.py
pyros_interfaces/mock/__init__.py
pyros_interfaces/mock/exceptions.py
pyros_interfaces/mock/mockinterface.py
pyros_interfaces/mock/mockmessage.py
pyros_interfaces/mock/mockparam.py
pyros_interfaces/mock/mockparampool.py
pyros_interfaces/mock/mockpublisher.py
pyros_interfaces/mock/mockpublisherpool.py
pyros_interfaces/mock/mockservice.py
pyros_interfaces/mock/mockservicepool.py
pyros_interfaces/mock/mocksubscriber.py
pyros_interfaces/mock/mocksubscriberpool.py
pyros_interfaces/mock/mocksystem.py
pyros_interfaces/mock/pyros_mock.py
pyros_interfaces/mock/tests/__init__.py
pyros_interfaces/mock/tests/test_mockinterface.py
pyros_interfaces/mock/tests/test_mockmessage.py
pyros_interfaces/mock/tests/test_mockparam.py
pyros_interfaces/mock/tests/test_mockservice.py
pyros_interfaces/mock/tests/test_mocktopic.py
pyros_interfaces/mock/tests/test_pyros_mock.py
pyros_interfaces.common-0.4.1.dist-info/DESCRIPTION.rst
pyros_interfaces.common-0.4.1.dist-info/METADATA
pyros_interfaces.common-0.4.1.dist-info/RECORD
pyros_interfaces.common-0.4.1.dist-info/WHEEL
pyros_interfaces.common-0.4.1.dist-info/metadata.json
pyros_interfaces.common-0.4.1.dist-info/namespace_packages.txt
pyros_interfaces.common-0.4.1.dist-info/top_level.txt
