Metadata-Version: 2.0
Name: pyros-interfaces.common
Version: 0.4.1
Summary: ROS Node to provide ROS introspection for non-ROS users.
Home-page: http://github.com/asmodehn/pyros
Author: AlexV
Author-email: asmodehn@gmail.com
License: BSD
Platform: UNKNOWN
Requires-Dist: mock (==1.0.1)
Requires-Dist: nose (>=1.3.7)
Requires-Dist: pyros-config (>=0.1.4)
Requires-Dist: pyros-setup (>=0.1.5)
Requires-Dist: pyzmp (>=0.0.14)
Requires-Dist: pyzmq
Requires-Dist: six
Requires-Dist: tblib
